geovista_slam-0.1.4.dist-info/licenses/LICENSE
slam/__init__.py
slam/_version.py
geovista_slam-0.1.4.dist-info/METADATA
geovista_slam-0.1.4.dist-info/WHEEL
geovista_slam-0.1.4.dist-info/top_level.txt
geovista_slam-0.1.4.dist-info/RECORD
