Metadata-Version: 2.4
Name: geovista-slam
Version: 0.1.4
Summary: Structured Local Area Model
Author-email: Bill Little <bjlittle.pub@gmail.com>
License: BSD-3-Clause
Project-URL: Code, https://github.com/bjlittle/geovista-slam
Project-URL: Issues, https://github.com/bjlittle/geovista-slam/issues
Keywords: curvilinear,earth-science,geovista,grid,lam,mesh,python,pyvista,rectilinear,ugrid,unstructured,vtk
Classifier: Development Status :: 1 - Planning
Classifier: Intended Audience :: Science/Research
Classifier: License :: OSI Approved :: BSD License
Classifier: Natural Language :: English
Classifier: Operating System :: OS Independent
Classifier: Programming Language :: Python :: 3 :: Only
Classifier: Programming Language :: Python :: 3.11
Classifier: Programming Language :: Python :: 3.12
Classifier: Topic :: Scientific/Engineering :: Atmospheric Science
Requires-Python: >=3.11
License-File: LICENSE
Requires-Dist: geovista<0.6,>=0.5.3
Requires-Dist: numpy<3,>=1.25.0
Requires-Dist: scitools-iris<4,>=3.12.0
Provides-Extra: dev
Requires-Dist: pre-commit<5,>=4.2.0; extra == "dev"
Requires-Dist: ruff<0.12.2,>=0.12.0; extra == "dev"
Requires-Dist: zizmor<1.10.1,>=1.9.0; extra == "dev"
Provides-Extra: test
Requires-Dist: pytest<9,>=8.3.5; extra == "test"
Dynamic: license-file
